secrets_getter/__init__.py
secrets_getter/exceptions.py
secrets_getter/secrets_getter.py
sld.secrets_getter-0.2.5.dist-info/AUTHORS.md
sld.secrets_getter-0.2.5.dist-info/LICENSE
sld.secrets_getter-0.2.5.dist-info/METADATA
sld.secrets_getter-0.2.5.dist-info/WHEEL
sld.secrets_getter-0.2.5.dist-info/top_level.txt
sld.secrets_getter-0.2.5.dist-info/RECORD
