Metadata-Version: 2.1
Name: sld.secrets-getter
Version: 0.2.5
Summary: Thin wrapper for the AWS Secrets Manager library. Allows for getting secrets in a standard way.
Home-page: https://github.com/SoldenServices/sld.secrets_getter
Author: Matthew Larsen
Author-email: matt.larsen@connorgp.com
License: MIT license
Keywords: Secrets Manager
Platform: UNKNOWN
Classifier: Development Status :: 2 - Pre-Alpha
Classifier: Intended Audience :: Developers
Classifier: License :: OSI Approved :: MIT License
Classifier: Natural Language :: English
Classifier: Programming Language :: Python :: 3
Classifier: Programming Language :: Python :: 3.6
Classifier: Programming Language :: Python :: 3.7
Classifier: Programming Language :: Python :: 3.8
Requires-Python: >=3.6
Requires-Dist: boto3
Requires-Dist: botocore
